{
    "os": "Linux-6.5.0-45-generic-x86_64-with-glibc2.35",
    "python": "3.10.12",
    "heartbeatAt": "2024-08-14T21:23:15.104768",
    "startedAt": "2024-08-14T21:23:13.217782",
    "docker": null,
    "cuda": null,
    "args": [],
    "state": "running",
    "program": "/home/aaderevyagin/airi_final/airi-screening-part-1/./scripts/compare_arena.py",
    "codePathLocal": "scripts/compare_arena.py",
    "codePath": "scripts/compare_arena.py",
    "git": {
        "remote": "git@github.com:Komershan/airi-screening-part-1.git",
        "commit": "6f26fc62997c0c9594e668d7836b807c69839d07"
    },
    "email": "derevyagin102@mail.ru",
    "root": "/home/aaderevyagin/airi_final/airi-screening-part-1",
    "host": "aaderevyagin-OMEN-by-HP-Laptop-16-c0xxx",
    "username": "aaderevyagin",
    "executable": "/home/aaderevyagin/airi_final/venv/bin/python3",
    "cpu_count": 8,
    "cpu_count_logical": 16,
    "cpu_freq": {
        "current": 3599.6069999999995,
        "min": 400.0,
        "max": 4463.0
    },
    "cpu_freq_per_core": [
        {
            "current": 3962.824,
            "min": 400.0,
            "max": 4463.0
        },
        {
            "current": 3935.023,
            "min": 400.0,
            "max": 4463.0
        },
        {
            "current": 4032.353,
            "min": 400.0,
            "max": 4463.0
        },
        {
            "current": 3948.066,
            "min": 400.0,
            "max": 4463.0
        },
        {
            "current": 3501.264,
            "min": 400.0,
            "max": 4463.0
        },
        {
            "current": 3825.622,
            "min": 400.0,
            "max": 4463.0
        },
        {
            "current": 400.0,
            "min": 400.0,
            "max": 4463.0
        },
        {
            "current": 4040.673,
            "min": 400.0,
            "max": 4463.0
        },
        {
            "current": 3933.177,
            "min": 400.0,
            "max": 4463.0
        },
        {
            "current": 4036.735,
            "min": 400.0,
            "max": 4463.0
        },
        {
            "current": 4046.192,
            "min": 400.0,
            "max": 4463.0
        },
        {
            "current": 4039.122,
            "min": 400.0,
            "max": 4463.0
        },
        {
            "current": 3234.794,
            "min": 400.0,
            "max": 4463.0
        },
        {
            "current": 3231.151,
            "min": 400.0,
            "max": 4463.0
        },
        {
            "current": 3416.054,
            "min": 400.0,
            "max": 4463.0
        },
        {
            "current": 3599.777,
            "min": 400.0,
            "max": 4463.0
        }
    ],
    "disk": {
        "/": {
            "total": 937.3305015563965,
            "used": 227.51578521728516
        }
    },
    "gpu": "NVIDIA GeForce RTX 3070 Laptop GPU",
    "gpu_count": 1,
    "gpu_devices": [
        {
            "name": "NVIDIA GeForce RTX 3070 Laptop GPU",
            "memory_total": 8589934592
        }
    ],
    "memory": {
        "total": 14.962696075439453
    }
}
