{
    "os": "Linux-6.5.0-45-generic-x86_64-with-glibc2.35",
    "python": "3.10.12",
    "heartbeatAt": "2024-08-14T08:27:06.153643",
    "startedAt": "2024-08-14T08:27:03.511745",
    "docker": null,
    "cuda": null,
    "args": [],
    "state": "running",
    "program": "/home/aaderevyagin/airi_final/airi-screening-part-1/./algorithms/in_context_learning/AD.py",
    "codePathLocal": "algorithms/in_context_learning/AD.py",
    "codePath": "algorithms/in_context_learning/AD.py",
    "git": {
        "remote": "git@github.com:Komershan/airi-screening-part-1.git",
        "commit": "6f26fc62997c0c9594e668d7836b807c69839d07"
    },
    "email": "derevyagin102@mail.ru",
    "root": "/home/aaderevyagin/airi_final/airi-screening-part-1",
    "host": "aaderevyagin-OMEN-by-HP-Laptop-16-c0xxx",
    "username": "aaderevyagin",
    "executable": "/home/aaderevyagin/airi_final/venv/bin/python3",
    "cpu_count": 8,
    "cpu_count_logical": 16,
    "cpu_freq": {
        "current": 2296.4265625,
        "min": 400.0,
        "max": 4463.0
    },
    "cpu_freq_per_core": [
        {
            "current": 3513.652,
            "min": 400.0,
            "max": 4463.0
        },
        {
            "current": 3524.864,
            "min": 400.0,
            "max": 4463.0
        },
        {
            "current": 3532.557,
            "min": 400.0,
            "max": 4463.0
        },
        {
            "current": 400.0,
            "min": 400.0,
            "max": 4463.0
        },
        {
            "current": 2364.706,
            "min": 400.0,
            "max": 4463.0
        },
        {
            "current": 4405.814,
            "min": 400.0,
            "max": 4463.0
        },
        {
            "current": 4274.495,
            "min": 400.0,
            "max": 4463.0
        },
        {
            "current": 2515.569,
            "min": 400.0,
            "max": 4463.0
        },
        {
            "current": 2879.888,
            "min": 400.0,
            "max": 4463.0
        },
        {
            "current": 400.0,
            "min": 400.0,
            "max": 4463.0
        },
        {
            "current": 400.0,
            "min": 400.0,
            "max": 4463.0
        },
        {
            "current": 4374.292,
            "min": 400.0,
            "max": 4463.0
        },
        {
            "current": 4387.419,
            "min": 400.0,
            "max": 4463.0
        },
        {
            "current": 400.0,
            "min": 400.0,
            "max": 4463.0
        },
        {
            "current": 4378.351,
            "min": 400.0,
            "max": 4463.0
        },
        {
            "current": 400.0,
            "min": 400.0,
            "max": 4463.0
        }
    ],
    "disk": {
        "/": {
            "total": 937.3305015563965,
            "used": 226.27776718139648
        }
    },
    "gpu": "NVIDIA GeForce RTX 3070 Laptop GPU",
    "gpu_count": 1,
    "gpu_devices": [
        {
            "name": "NVIDIA GeForce RTX 3070 Laptop GPU",
            "memory_total": 8589934592
        }
    ],
    "memory": {
        "total": 14.962696075439453
    }
}
