{
    "os": "Linux-6.5.0-45-generic-x86_64-with-glibc2.35",
    "python": "3.10.12",
    "heartbeatAt": "2024-08-15T03:13:13.192000",
    "startedAt": "2024-08-15T03:13:11.003780",
    "docker": null,
    "cuda": null,
    "args": [],
    "state": "running",
    "program": "/home/aaderevyagin/airi_final/airi-screening-part-1/./scripts/compare_arena.py",
    "codePathLocal": "scripts/compare_arena.py",
    "codePath": "scripts/compare_arena.py",
    "git": {
        "remote": "git@github.com:Komershan/airi-screening-part-1.git",
        "commit": "6f26fc62997c0c9594e668d7836b807c69839d07"
    },
    "email": "derevyagin102@mail.ru",
    "root": "/home/aaderevyagin/airi_final/airi-screening-part-1",
    "host": "aaderevyagin-OMEN-by-HP-Laptop-16-c0xxx",
    "username": "aaderevyagin",
    "executable": "/home/aaderevyagin/airi_final/venv/bin/python3",
    "cpu_count": 8,
    "cpu_count_logical": 16,
    "cpu_freq": {
        "current": 3476.295125,
        "min": 400.0,
        "max": 4463.0
    },
    "cpu_freq_per_core": [
        {
            "current": 3801.656,
            "min": 400.0,
            "max": 4463.0
        },
        {
            "current": 3541.976,
            "min": 400.0,
            "max": 4463.0
        },
        {
            "current": 3978.109,
            "min": 400.0,
            "max": 4463.0
        },
        {
            "current": 3392.626,
            "min": 400.0,
            "max": 4463.0
        },
        {
            "current": 4299.01,
            "min": 400.0,
            "max": 4463.0
        },
        {
            "current": 4267.4,
            "min": 400.0,
            "max": 4463.0
        },
        {
            "current": 4303.229,
            "min": 400.0,
            "max": 4463.0
        },
        {
            "current": 4257.185,
            "min": 400.0,
            "max": 4463.0
        },
        {
            "current": 3989.211,
            "min": 400.0,
            "max": 4463.0
        },
        {
            "current": 400.0,
            "min": 400.0,
            "max": 4463.0
        },
        {
            "current": 3720.583,
            "min": 400.0,
            "max": 4463.0
        },
        {
            "current": 3688.002,
            "min": 400.0,
            "max": 4463.0
        },
        {
            "current": 4287.354,
            "min": 400.0,
            "max": 4463.0
        },
        {
            "current": 400.0,
            "min": 400.0,
            "max": 4463.0
        },
        {
            "current": 4044.728,
            "min": 400.0,
            "max": 4463.0
        },
        {
            "current": 3249.653,
            "min": 400.0,
            "max": 4463.0
        }
    ],
    "disk": {
        "/": {
            "total": 937.3305015563965,
            "used": 228.4262237548828
        }
    },
    "gpu": "NVIDIA GeForce RTX 3070 Laptop GPU",
    "gpu_count": 1,
    "gpu_devices": [
        {
            "name": "NVIDIA GeForce RTX 3070 Laptop GPU",
            "memory_total": 8589934592
        }
    ],
    "memory": {
        "total": 14.962711334228516
    }
}
