{
    "os": "Linux-6.5.0-45-generic-x86_64-with-glibc2.35",
    "python": "3.10.12",
    "heartbeatAt": "2024-08-14T07:43:38.189103",
    "startedAt": "2024-08-14T07:43:36.464609",
    "docker": null,
    "cuda": null,
    "args": [],
    "state": "running",
    "program": "/home/aaderevyagin/airi_final/airi-screening-part-1/./scripts/compare_arena.py",
    "codePathLocal": "scripts/compare_arena.py",
    "codePath": "scripts/compare_arena.py",
    "git": {
        "remote": "git@github.com:Komershan/airi-screening-part-1.git",
        "commit": "6f26fc62997c0c9594e668d7836b807c69839d07"
    },
    "email": "derevyagin102@mail.ru",
    "root": "/home/aaderevyagin/airi_final/airi-screening-part-1",
    "host": "aaderevyagin-OMEN-by-HP-Laptop-16-c0xxx",
    "username": "aaderevyagin",
    "executable": "/home/aaderevyagin/airi_final/venv/bin/python3",
    "cpu_count": 8,
    "cpu_count_logical": 16,
    "cpu_freq": {
        "current": 2623.0645624999997,
        "min": 400.0,
        "max": 4463.0
    },
    "cpu_freq_per_core": [
        {
            "current": 400.0,
            "min": 400.0,
            "max": 4463.0
        },
        {
            "current": 4127.826,
            "min": 400.0,
            "max": 4463.0
        },
        {
            "current": 3592.658,
            "min": 400.0,
            "max": 4463.0
        },
        {
            "current": 4367.788,
            "min": 400.0,
            "max": 4463.0
        },
        {
            "current": 4296.916,
            "min": 400.0,
            "max": 4463.0
        },
        {
            "current": 400.0,
            "min": 400.0,
            "max": 4463.0
        },
        {
            "current": 4373.709,
            "min": 400.0,
            "max": 4463.0
        },
        {
            "current": 4370.72,
            "min": 400.0,
            "max": 4463.0
        },
        {
            "current": 3568.676,
            "min": 400.0,
            "max": 4463.0
        },
        {
            "current": 400.0,
            "min": 400.0,
            "max": 4463.0
        },
        {
            "current": 2136.653,
            "min": 400.0,
            "max": 4463.0
        },
        {
            "current": 4358.868,
            "min": 400.0,
            "max": 4463.0
        },
        {
            "current": 4373.268,
            "min": 400.0,
            "max": 4463.0
        },
        {
            "current": 400.0,
            "min": 400.0,
            "max": 4463.0
        },
        {
            "current": 3488.176,
            "min": 400.0,
            "max": 4463.0
        },
        {
            "current": 400.0,
            "min": 400.0,
            "max": 4463.0
        }
    ],
    "disk": {
        "/": {
            "total": 937.3305015563965,
            "used": 226.01039505004883
        }
    },
    "gpu": "NVIDIA GeForce RTX 3070 Laptop GPU",
    "gpu_count": 1,
    "gpu_devices": [
        {
            "name": "NVIDIA GeForce RTX 3070 Laptop GPU",
            "memory_total": 8589934592
        }
    ],
    "memory": {
        "total": 14.962696075439453
    }
}
