{
    "os": "Linux-6.8.0-40-generic-x86_64-with-glibc2.35",
    "python": "3.10.12",
    "heartbeatAt": "2024-08-15T15:56:39.644755",
    "startedAt": "2024-08-15T15:56:38.500237",
    "docker": null,
    "cuda": null,
    "args": [],
    "state": "running",
    "program": "/home/aaderevyagin/airi_final/airi-screening-part-1/./scripts/data_generation.py",
    "codePathLocal": "scripts/data_generation.py",
    "codePath": "scripts/data_generation.py",
    "git": {
        "remote": "git@github.com:Komershan/airi-screening-part-1.git",
        "commit": "6f26fc62997c0c9594e668d7836b807c69839d07"
    },
    "email": "derevyagin102@mail.ru",
    "root": "/home/aaderevyagin/airi_final/airi-screening-part-1",
    "host": "aaderevyagin-OMEN-by-HP-Laptop-16-c0xxx",
    "username": "aaderevyagin",
    "executable": "/home/aaderevyagin/airi_final/venv/bin/python3",
    "cpu_count": 8,
    "cpu_count_logical": 16,
    "cpu_freq": {
        "current": 3302.742875,
        "min": 400.0,
        "max": 4463.0
    },
    "cpu_freq_per_core": [
        {
            "current": 3357.471,
            "min": 400.0,
            "max": 4463.0
        },
        {
            "current": 400.0,
            "min": 400.0,
            "max": 4463.0
        },
        {
            "current": 4152.702,
            "min": 400.0,
            "max": 4463.0
        },
        {
            "current": 400.0,
            "min": 400.0,
            "max": 4463.0
        },
        {
            "current": 4207.433,
            "min": 400.0,
            "max": 4463.0
        },
        {
            "current": 3776.042,
            "min": 400.0,
            "max": 4463.0
        },
        {
            "current": 3009.164,
            "min": 400.0,
            "max": 4463.0
        },
        {
            "current": 3358.616,
            "min": 400.0,
            "max": 4463.0
        },
        {
            "current": 3722.848,
            "min": 400.0,
            "max": 4463.0
        },
        {
            "current": 400.0,
            "min": 400.0,
            "max": 4463.0
        },
        {
            "current": 3391.249,
            "min": 400.0,
            "max": 4463.0
        },
        {
            "current": 4294.2,
            "min": 400.0,
            "max": 4463.0
        },
        {
            "current": 3872.303,
            "min": 400.0,
            "max": 4463.0
        },
        {
            "current": 3691.148,
            "min": 400.0,
            "max": 4463.0
        },
        {
            "current": 3744.425,
            "min": 400.0,
            "max": 4463.0
        },
        {
            "current": 4118.259,
            "min": 400.0,
            "max": 4463.0
        }
    ],
    "disk": {
        "/": {
            "total": 937.3305015563965,
            "used": 229.87376022338867
        }
    },
    "memory": {
        "total": 14.970542907714844
    }
}
