{
    "os": "Linux-6.8.0-40-generic-x86_64-with-glibc2.35",
    "python": "3.10.12",
    "heartbeatAt": "2024-08-16T04:02:41.666948",
    "startedAt": "2024-08-16T04:02:39.706496",
    "docker": null,
    "cuda": null,
    "args": [],
    "state": "running",
    "program": "/home/aaderevyagin/airi_final/airi-screening-part-1/./scripts/compare_arena.py",
    "codePathLocal": "scripts/compare_arena.py",
    "codePath": "scripts/compare_arena.py",
    "git": {
        "remote": "git@github.com:Komershan/airi-screening-part-1.git",
        "commit": "9bd04645b835810220e6c408b3d220101a158cc7"
    },
    "email": "derevyagin102@mail.ru",
    "root": "/home/aaderevyagin/airi_final/airi-screening-part-1",
    "host": "aaderevyagin-OMEN-by-HP-Laptop-16-c0xxx",
    "username": "aaderevyagin",
    "executable": "/home/aaderevyagin/airi_final/venv/bin/python3",
    "cpu_count": 8,
    "cpu_count_logical": 16,
    "cpu_freq": {
        "current": 2930.456625,
        "min": 400.0,
        "max": 4463.0
    },
    "cpu_freq_per_core": [
        {
            "current": 3405.838,
            "min": 400.0,
            "max": 4463.0
        },
        {
            "current": 3412.527,
            "min": 400.0,
            "max": 4463.0
        },
        {
            "current": 4096.185,
            "min": 400.0,
            "max": 4463.0
        },
        {
            "current": 400.0,
            "min": 400.0,
            "max": 4463.0
        },
        {
            "current": 3629.202,
            "min": 400.0,
            "max": 4463.0
        },
        {
            "current": 2635.193,
            "min": 400.0,
            "max": 4463.0
        },
        {
            "current": 4263.639,
            "min": 400.0,
            "max": 4463.0
        },
        {
            "current": 400.0,
            "min": 400.0,
            "max": 4463.0
        },
        {
            "current": 3929.83,
            "min": 400.0,
            "max": 4463.0
        },
        {
            "current": 3400.532,
            "min": 400.0,
            "max": 4463.0
        },
        {
            "current": 4279.839,
            "min": 400.0,
            "max": 4463.0
        },
        {
            "current": 3628.965,
            "min": 400.0,
            "max": 4463.0
        },
        {
            "current": 3398.165,
            "min": 400.0,
            "max": 4463.0
        },
        {
            "current": 400.0,
            "min": 400.0,
            "max": 4463.0
        },
        {
            "current": 400.0,
            "min": 400.0,
            "max": 4463.0
        },
        {
            "current": 3397.983,
            "min": 400.0,
            "max": 4463.0
        }
    ],
    "disk": {
        "/": {
            "total": 937.3305015563965,
            "used": 231.1237564086914
        }
    },
    "memory": {
        "total": 14.970539093017578
    }
}
