{
    "os": "Linux-6.5.0-45-generic-x86_64-with-glibc2.35",
    "python": "3.10.12",
    "heartbeatAt": "2024-08-14T22:13:57.142280",
    "startedAt": "2024-08-14T22:13:54.626169",
    "docker": null,
    "cuda": null,
    "args": [],
    "state": "running",
    "program": "/home/aaderevyagin/airi_final/airi-screening-part-1/./scripts/data_generation.py",
    "codePathLocal": "scripts/data_generation.py",
    "codePath": "scripts/data_generation.py",
    "git": {
        "remote": "git@github.com:Komershan/airi-screening-part-1.git",
        "commit": "6f26fc62997c0c9594e668d7836b807c69839d07"
    },
    "email": "derevyagin102@mail.ru",
    "root": "/home/aaderevyagin/airi_final/airi-screening-part-1",
    "host": "aaderevyagin-OMEN-by-HP-Laptop-16-c0xxx",
    "username": "aaderevyagin",
    "executable": "/home/aaderevyagin/airi_final/venv/bin/python3",
    "cpu_count": 8,
    "cpu_count_logical": 16,
    "cpu_freq": {
        "current": 3351.0059375,
        "min": 400.0,
        "max": 4463.0
    },
    "cpu_freq_per_core": [
        {
            "current": 3328.081,
            "min": 400.0,
            "max": 4463.0
        },
        {
            "current": 3657.089,
            "min": 400.0,
            "max": 4463.0
        },
        {
            "current": 4167.868,
            "min": 400.0,
            "max": 4463.0
        },
        {
            "current": 400.0,
            "min": 400.0,
            "max": 4463.0
        },
        {
            "current": 4079.904,
            "min": 400.0,
            "max": 4463.0
        },
        {
            "current": 4135.254,
            "min": 400.0,
            "max": 4463.0
        },
        {
            "current": 3585.059,
            "min": 400.0,
            "max": 4463.0
        },
        {
            "current": 3479.483,
            "min": 400.0,
            "max": 4463.0
        },
        {
            "current": 4176.929,
            "min": 400.0,
            "max": 4463.0
        },
        {
            "current": 400.0,
            "min": 400.0,
            "max": 4463.0
        },
        {
            "current": 3838.694,
            "min": 400.0,
            "max": 4463.0
        },
        {
            "current": 3959.898,
            "min": 400.0,
            "max": 4463.0
        },
        {
            "current": 3967.679,
            "min": 400.0,
            "max": 4463.0
        },
        {
            "current": 4177.585,
            "min": 400.0,
            "max": 4463.0
        },
        {
            "current": 3732.274,
            "min": 400.0,
            "max": 4463.0
        },
        {
            "current": 3968.85,
            "min": 400.0,
            "max": 4463.0
        }
    ],
    "disk": {
        "/": {
            "total": 937.3305015563965,
            "used": 227.51470947265625
        }
    },
    "gpu": "NVIDIA GeForce RTX 3070 Laptop GPU",
    "gpu_count": 1,
    "gpu_devices": [
        {
            "name": "NVIDIA GeForce RTX 3070 Laptop GPU",
            "memory_total": 8589934592
        }
    ],
    "memory": {
        "total": 14.962696075439453
    }
}
